systemd_generator/__init__.py
generate_systemd_timer-0.1.3.dist-info/METADATA
generate_systemd_timer-0.1.3.dist-info/WHEEL
generate_systemd_timer-0.1.3.dist-info/entry_points.txt
generate_systemd_timer-0.1.3.dist-info/RECORD
